{"title":"BLACKPINK ─ TikTok","url":"https://www.tiktok.com/@bp_tiktok?","favicon":"https://www.tiktok.com/favicon.ico","elements":[{"title":"","contents":"<div class=\"jsx-2261688415 _ratio_\"><div style=\"padding-top: 132.653%;\" class=\"jsx-2261688415\"><div class=\"jsx-2261688415 _ratio_wrapper\"><a href=\"https://www.tiktok.com/@bp_tiktok/video/6990210408686587137\" class=\"jsx-3808264675 video-feed-item-wrapper\"><span class=\"lazyload-wrapper\"><div style=\"border-radius: 0px; background-image: url(&quot;https://p16-sign-sg.tiktokcdn.com/obj/tos-alisg-p-0037/a978f575d7164c20903d2782ea350e71?x-expires=1629579600&amp;x-signature=X0%2FQ9dn36SfiX6FhvsfjTx8Rf7w%3D&quot;);\" class=\"jsx-828470630 image-card\"><div class=\"jsx-969240130 video-card default\"><video region=\"US\" webkit-playsinline=\"true\" playsinline=\"\" loop=\"\" likes=\"\" src=\"https://v16-web.tiktok.com/video/tos/alisg/tos-alisg-pve-0037/6846b43b15e24df7a063340c44baab53/?a=1988&amp;br=734&amp;bt=367&amp;cd=0%7C0%7C1&amp;ch=0&amp;cr=0&amp;cs=0&amp;cv=1&amp;dr=3&amp;ds=3&amp;er=&amp;expire=1629580412&amp;ft=Q9BExEXk_4ka&amp;l=202108211513000101880612035E69FB25&amp;lr=tiktok&amp;mime_type=video_mp4&amp;net=0&amp;pl=0&amp;policy=3&amp;qs=0&amp;rc=anZ0amQ6Zmw2NzMzODgzNEApNGY2N2hoNDszNzw3PDhkNWdeNC0wcjRfYi5gLS1kLy1zczNeYTUzNC0yMC5eYjEyNWM6Yw%3D%3D&amp;signature=e621f6b53e053b1539759d43c2205c5d&amp;tk=0&amp;vl=&amp;vr=\" volume=\"0\" seektime=\"0\" preload=\"metadata\" class=\"jsx-3900254205 video-player\"></video><div class=\"jsx-969240130 video-card-mask\"><div class=\"jsx-3239500515 card-footer normal no-avatar\"><div class=\"jsx-3239500515 video-bottom-info\"></div></div></div></div></div></span></a></div></div></div><div class=\"jsx-526152079 card-bottom-info\"><div class=\"meta-caption-line\"><h3 class=\"jsx-2276759325 video-meta-title\"><strong class=\"jsx-2276759325\">BLACKPINK THE MOVIE - TICKET SALES OPENING IN SOUTH KOREA#</strong><a href=\"/tag/blackpink?lang=en\" class=\"tag-link jsx-231826672\" rel=\"noopener\"><strong class=\"jsx-231826672\">BLACKPINK  </strong></a><strong class=\"jsx-2276759325\">#</strong><a href=\"/tag/%EB%B8%94%EB%9E%99%ED%95%91%ED%81%AC?lang=en\" class=\"tag-link jsx-231826672\" rel=\"noopener\"><strong class=\"jsx-231826672\">블랙핑크  </strong></a><strong class=\"jsx-2276759325\">#</strong><a href=\"/tag/the_movie?lang=en\" class=\"tag-link jsx-231826672\" rel=\"noopener\"><strong class=\"jsx-231826672\">THE_MOVIE  </strong></a><strong class=\"jsx-2276759325\">#</strong><a href=\"/tag/20210804?lang=en\" class=\"tag-link jsx-231826672\" rel=\"noopener\"><strong class=\"jsx-231826672\">20210804  </strong></a><strong class=\"jsx-2276759325\">#</strong><a href=\"/tag/5thanniversary?lang=en\" class=\"tag-link jsx-231826672\" rel=\"noopener\"><strong class=\"jsx-231826672\">5thANNIVERSARY  </strong></a><strong class=\"jsx-2276759325\">#</strong><a href=\"/tag/4plus1_project?lang=en\" class=\"tag-link jsx-231826672\" rel=\"noopener\"><strong class=\"jsx-231826672\">4PLUS1_PROJECT  </strong></a><strong class=\"jsx-2276759325\">#</strong><a href=\"/tag/yg?lang=en\" class=\"tag-link jsx-231826672\" rel=\"noopener\"><strong class=\"jsx-231826672\">YG  </strong></a><strong class=\"jsx-2276759325\">#</strong><a href=\"/tag/cj4dplex?lang=en\" class=\"tag-link jsx-231826672\" rel=\"noopener\"><strong class=\"jsx-231826672\">CJ4DPLEX  </strong></a><strong class=\"jsx-2276759325\">#</strong><a href=\"/tag/cgv?lang=en\" class=\"tag-link jsx-231826672\" rel=\"noopener\"><strong class=\"jsx-231826672\">CGV </strong></a></h3></div><div class=\"jsx-526152079 play-line\"><div class=\"jsx-526152079 play-icon\"><svg class=\"like-icon\" width=\"16\" height=\"16\" viewBox=\"0 0 48 48\" fill=\"rgba(22, 24, 35, 0.75)\" xmlns=\"http://www.w3.org/2000/svg\"><path fill-rule=\"evenodd\" clip-rule=\"evenodd\" d=\"M16 10.554V37.4459L38.1463 24L16 10.554ZM12 8.77702C12 6.43812 14.5577 4.99881 16.5569 6.21266L41.6301 21.4356C43.5542 22.6038 43.5542 25.3962 41.6301 26.5644L16.5569 41.7873C14.5577 43.0012 12 41.5619 12 39.223V8.77702Z\"></path></svg><strong class=\"jsx-526152079 video-count\">2.9M</strong></div><div class=\"jsx-526152079\">7-29</div></div></div>","link":"https://www.tiktok.com/@bp_tiktok/video/6990210408686587137","retrieved":1629558382536,"image":"https://p16-sign-sg.tiktokcdn.com/obj/tos-alisg-p-0037/a978f575d7164c20903d2782ea350e71?x-expires=1629579600&x-signature=X0%2FQ9dn36SfiX6FhvsfjTx8Rf7w%3D"},{"title":"","contents":"<div class=\"jsx-2261688415 _ratio_\"><div style=\"padding-top: 132.653%;\" class=\"jsx-2261688415\"><div class=\"jsx-2261688415 _ratio_wrapper\"><a href=\"https://www.tiktok.com/@bp_tiktok/video/6989899774593944833\" class=\"jsx-3808264675 video-feed-item-wrapper\"><span class=\"lazyload-wrapper\"><div style=\"border-radius: 0px; background-image: url(&quot;https://p16-sign-sg.tiktokcdn.com/obj/tos-alisg-p-0037/3506b603d47e47d69edb214772ae98bf_1627462872?x-expires=1629579600&amp;x-signature=nlvx2%2Brj4FDCZvW2l5AxumdUOJ8%3D&quot;);\" class=\"jsx-828470630 image-card\"><div class=\"jsx-969240130 video-card default\"><div class=\"jsx-969240130 video-card-mask\"><div class=\"jsx-3239500515 card-footer normal no-avatar\"><div class=\"jsx-3239500515 video-bottom-info\"></div></div></div></div></div></span></a></div></div></div><div class=\"jsx-526152079 card-bottom-info\"><div class=\"meta-caption-line\"><h3 class=\"jsx-2276759325 video-meta-title\"><strong class=\"jsx-2276759325\">BLACKPINK - 5th ANNIVERSARY [4+1] THE MOVIE SCREENX TRAILER On Aug 4th, It’s time to meet BLACKPINK in your cinema! </strong><a href=\"/tag/blackpink?lang=en\" class=\"tag-link jsx-231826672\" rel=\"noopener\"><strong class=\"jsx-231826672\">#BLACKPINK </strong></a><strong class=\"jsx-2276759325\"> </strong><a href=\"/tag/%EB%B8%94%EB%9E%99%ED%95%91%ED%81%AC?lang=en\" class=\"tag-link jsx-231826672\" rel=\"noopener\"><strong class=\"jsx-231826672\">#블랙핑크 </strong></a><strong class=\"jsx-2276759325\"> </strong><a href=\"/tag/the_movie?lang=en\" class=\"tag-link jsx-231826672\" rel=\"noopener\"><strong class=\"jsx-231826672\">#THE_MOVIE </strong></a><strong class=\"jsx-2276759325\"> </strong><a href=\"/tag/yg?lang=en\" class=\"tag-link jsx-231826672\" rel=\"noopener\"><strong class=\"jsx-231826672\">#YG </strong></a></h3></div><div class=\"jsx-526152079 play-line\"><div class=\"jsx-526152079 play-icon\"><svg class=\"like-icon\" width=\"16\" height=\"16\" viewBox=\"0 0 48 48\" fill=\"rgba(22, 24, 35, 0.75)\" xmlns=\"http://www.w3.org/2000/svg\"><path fill-rule=\"evenodd\" clip-rule=\"evenodd\" d=\"M16 10.554V37.4459L38.1463 24L16 10.554ZM12 8.77702C12 6.43812 14.5577 4.99881 16.5569 6.21266L41.6301 21.4356C43.5542 22.6038 43.5542 25.3962 41.6301 26.5644L16.5569 41.7873C14.5577 43.0012 12 41.5619 12 39.223V8.77702Z\"></path></svg><strong class=\"jsx-526152079 video-count\">2.7M</strong></div><div class=\"jsx-526152079\">7-28</div></div></div>","link":"https://www.tiktok.com/@bp_tiktok/video/6989899774593944833","retrieved":1629558382526,"image":"https://p16-sign-sg.tiktokcdn.com/obj/tos-alisg-p-0037/3506b603d47e47d69edb214772ae98bf_1627462872?x-expires=1629579600&x-signature=nlvx2%2Brj4FDCZvW2l5AxumdUOJ8%3D"},{"title":"","contents":"<div class=\"jsx-2261688415 _ratio_\"><div style=\"padding-top: 132.653%;\" class=\"jsx-2261688415\"><div class=\"jsx-2261688415 _ratio_wrapper\"><a href=\"https://www.tiktok.com/@bp_tiktok/video/6984704780379720962\" class=\"jsx-3808264675 video-feed-item-wrapper\"><span class=\"lazyload-wrapper\"><div style=\"border-radius: 0px; background-image: url(&quot;https://p16-sign-sg.tiktokcdn.com/obj/tos-alisg-p-0037/e3f1ff0a8a4d4184afdee32e2dd91c17_1626253331?x-expires=1629579600&amp;x-signature=lguAhZhEAuMRDIOKu4dZ3GN%2FR4o%3D&quot;);\" class=\"jsx-828470630 image-card\"><div class=\"jsx-969240130 video-card default\"><div class=\"jsx-969240130 video-card-mask\"><div class=\"jsx-3239500515 card-footer normal no-avatar\"><div class=\"jsx-3239500515 video-bottom-info\"></div></div></div></div></div></span></a></div></div></div><div class=\"jsx-526152079 card-bottom-info\"><div class=\"meta-caption-line\"><h3 class=\"jsx-2276759325 video-meta-title\"><a href=\"/tag/blackpink?lang=en\" class=\"tag-link jsx-231826672\" rel=\"noopener\"><strong class=\"jsx-231826672\">#BLACKPINK </strong></a><strong class=\"jsx-2276759325\"> – 5th ANNIVERSARY [4+1] THE MOVIE MAIN TRAILER Tickets still available at blackpinkthemovie.comMore info @ 5th.blackpinkofficial.com</strong></h3></div><div class=\"jsx-526152079 play-line\"><div class=\"jsx-526152079 play-icon\"><svg class=\"like-icon\" width=\"16\" height=\"16\" viewBox=\"0 0 48 48\" fill=\"rgba(22, 24, 35, 0.75)\" xmlns=\"http://www.w3.org/2000/svg\"><path fill-rule=\"evenodd\" clip-rule=\"evenodd\" d=\"M16 10.554V37.4459L38.1463 24L16 10.554ZM12 8.77702C12 6.43812 14.5577 4.99881 16.5569 6.21266L41.6301 21.4356C43.5542 22.6038 43.5542 25.3962 41.6301 26.5644L16.5569 41.7873C14.5577 43.0012 12 41.5619 12 39.223V8.77702Z\"></path></svg><strong class=\"jsx-526152079 video-count\">3.1M</strong></div><div class=\"jsx-526152079\">7-14</div></div></div>","link":"https://www.tiktok.com/@bp_tiktok/video/6984704780379720962","retrieved":1629558382526,"image":"https://p16-sign-sg.tiktokcdn.com/obj/tos-alisg-p-0037/e3f1ff0a8a4d4184afdee32e2dd91c17_1626253331?x-expires=1629579600&x-signature=lguAhZhEAuMRDIOKu4dZ3GN%2FR4o%3D"},{"title":"","contents":"<div class=\"jsx-2261688415 _ratio_\"><div style=\"padding-top: 132.653%;\" class=\"jsx-2261688415\"><div class=\"jsx-2261688415 _ratio_wrapper\"><a href=\"https://www.tiktok.com/@bp_tiktok/video/6979386024363412737\" class=\"jsx-3808264675 video-feed-item-wrapper\"><span class=\"lazyload-wrapper\"><div style=\"border-radius: 0px; background-image: url(&quot;https://p16-sign-sg.tiktokcdn.com/obj/tos-alisg-p-0037/73ea3cb98891461fa68f783d182796ec?x-expires=1629579600&amp;x-signature=5ynvTE0s0h3wnVoKD2GPRiMuBXg%3D&quot;);\" class=\"jsx-828470630 image-card\"><div class=\"jsx-969240130 video-card default\"><div class=\"jsx-969240130 video-card-mask\"><div class=\"jsx-3239500515 card-footer normal no-avatar\"><div class=\"jsx-3239500515 video-bottom-info\"></div></div></div></div></div></span></a></div></div></div><div class=\"jsx-526152079 card-bottom-info\"><div class=\"meta-caption-line\"><h3 class=\"jsx-2276759325 video-meta-title\"><strong class=\"jsx-2276759325\">SAVE YOUR SEATS! TICKETS NOW AVAILABLE via blackpinkthemovie.com </strong><a href=\"/tag/blackpinkinyourcinema?lang=en\" class=\"tag-link jsx-231826672\" rel=\"noopener\"><strong class=\"jsx-231826672\">#BLACKPINKINYOURCINEMA </strong></a></h3></div><div class=\"jsx-526152079 play-line\"><div class=\"jsx-526152079 play-icon\"><svg class=\"like-icon\" width=\"16\" height=\"16\" viewBox=\"0 0 48 48\" fill=\"rgba(22, 24, 35, 0.75)\" xmlns=\"http://www.w3.org/2000/svg\"><path fill-rule=\"evenodd\" clip-rule=\"evenodd\" d=\"M16 10.554V37.4459L38.1463 24L16 10.554ZM12 8.77702C12 6.43812 14.5577 4.99881 16.5569 6.21266L41.6301 21.4356C43.5542 22.6038 43.5542 25.3962 41.6301 26.5644L16.5569 41.7873C14.5577 43.0012 12 41.5619 12 39.223V8.77702Z\"></path></svg><strong class=\"jsx-526152079 video-count\">5.2M</strong></div><div class=\"jsx-526152079\">6-30</div></div></div>","link":"https://www.tiktok.com/@bp_tiktok/video/6979386024363412737","retrieved":1629558382528,"image":"https://p16-sign-sg.tiktokcdn.com/obj/tos-alisg-p-0037/73ea3cb98891461fa68f783d182796ec?x-expires=1629579600&x-signature=5ynvTE0s0h3wnVoKD2GPRiMuBXg%3D"},{"title":"","contents":"<div class=\"jsx-2261688415 _ratio_\"><div style=\"padding-top: 132.653%;\" class=\"jsx-2261688415\"><div class=\"jsx-2261688415 _ratio_wrapper\"><a href=\"https://www.tiktok.com/@bp_tiktok/video/6977375746528464129\" class=\"jsx-3808264675 video-feed-item-wrapper\"><span class=\"lazyload-wrapper\"><div style=\"border-radius: 0px; background-image: url(&quot;https://p16-sign-sg.tiktokcdn.com/obj/tos-alisg-p-0037/d2ddcdf370e2460ba66a635901cee390_1624546890?x-expires=1629579600&amp;x-signature=msV5CTGt9E2AgDtFvNQhTdHW8Do%3D&quot;);\" class=\"jsx-828470630 image-card\"><div class=\"jsx-969240130 video-card default\"><div class=\"jsx-969240130 video-card-mask\"><div class=\"jsx-3239500515 card-footer normal no-avatar\"><div class=\"jsx-3239500515 video-bottom-info\"></div></div></div></div></div></span></a></div></div></div><div class=\"jsx-526152079 card-bottom-info\"><div class=\"meta-caption-line\"><h3 class=\"jsx-2276759325 video-meta-title\"><strong class=\"jsx-2276759325\">Where Hits Are Made </strong><a href=\"/tag/todaystophits?lang=en\" class=\"tag-link jsx-231826672\" rel=\"noopener\"><strong class=\"jsx-231826672\">#TodaysTopHits </strong></a><strong class=\"jsx-2276759325\"> @spotify</strong></h3></div><div class=\"jsx-526152079 play-line\"><div class=\"jsx-526152079 play-icon\"><svg class=\"like-icon\" width=\"16\" height=\"16\" viewBox=\"0 0 48 48\" fill=\"rgba(22, 24, 35, 0.75)\" xmlns=\"http://www.w3.org/2000/svg\"><path fill-rule=\"evenodd\" clip-rule=\"evenodd\" d=\"M16 10.554V37.4459L38.1463 24L16 10.554ZM12 8.77702C12 6.43812 14.5577 4.99881 16.5569 6.21266L41.6301 21.4356C43.5542 22.6038 43.5542 25.3962 41.6301 26.5644L16.5569 41.7873C14.5577 43.0012 12 41.5619 12 39.223V8.77702Z\"></path></svg><strong class=\"jsx-526152079 video-count\">6.1M</strong></div><div class=\"jsx-526152079\">6-24</div></div></div>","link":"https://www.tiktok.com/@bp_tiktok/video/6977375746528464129","retrieved":1629558382529,"image":"https://p16-sign-sg.tiktokcdn.com/obj/tos-alisg-p-0037/d2ddcdf370e2460ba66a635901cee390_1624546890?x-expires=1629579600&x-signature=msV5CTGt9E2AgDtFvNQhTdHW8Do%3D"},{"title":"","contents":"<div class=\"jsx-2261688415 _ratio_\"><div style=\"padding-top: 132.653%;\" class=\"jsx-2261688415\"><div class=\"jsx-2261688415 _ratio_wrapper\"><a href=\"https://www.tiktok.com/@bp_tiktok/video/6976919772369816834\" class=\"jsx-3808264675 video-feed-item-wrapper\"><span class=\"lazyload-wrapper\"><div style=\"border-radius: 0px; background-image: url(&quot;https://p16-sign-sg.tiktokcdn.com/obj/tos-alisg-p-0037/5acbf4bf06fc449eb3f71ce31972fd51_1624440747?x-expires=1629579600&amp;x-signature=VQolBPbAn8XGulKljBcYaSQBrRc%3D&quot;);\" class=\"jsx-828470630 image-card horizontal\"><div class=\"jsx-969240130 video-card default\"><div class=\"jsx-969240130 video-card-mask\"><div class=\"jsx-3239500515 card-footer normal no-avatar\"><div class=\"jsx-3239500515 video-bottom-info\"></div></div></div></div></div></span></a></div></div></div><div class=\"jsx-526152079 card-bottom-info\"><div class=\"meta-caption-line\"><h3 class=\"jsx-2276759325 video-meta-title\"><strong class=\"jsx-2276759325\">BLACKPINK - 5th ANNIVERSARY [4+1 PROJECT] ANNOUNCEMENT VIDEO. More info @ 5th.blackpinkofficial.com </strong><a href=\"/tag/blackpink?lang=en\" class=\"tag-link jsx-231826672\" rel=\"noopener\"><strong class=\"jsx-231826672\">#BLACKPINK </strong></a><strong class=\"jsx-2276759325\"> </strong><a href=\"/tag/%EB%B8%94%EB%9E%99%ED%95%91%ED%81%AC?lang=en\" class=\"tag-link jsx-231826672\" rel=\"noopener\"><strong class=\"jsx-231826672\">#블랙핑크 </strong></a><strong class=\"jsx-2276759325\"> </strong><a href=\"/tag/5thanniversary?lang=en\" class=\"tag-link jsx-231826672\" rel=\"noopener\"><strong class=\"jsx-231826672\">#5thANNIVERSARY </strong></a><strong class=\"jsx-2276759325\"> </strong><a href=\"/tag/4plus1_project?lang=en\" class=\"tag-link jsx-231826672\" rel=\"noopener\"><strong class=\"jsx-231826672\">#4PLUS1_PROJECT </strong></a></h3></div><div class=\"jsx-526152079 play-line\"><div class=\"jsx-526152079 play-icon\"><svg class=\"like-icon\" width=\"16\" height=\"16\" viewBox=\"0 0 48 48\" fill=\"rgba(22, 24, 35, 0.75)\" xmlns=\"http://www.w3.org/2000/svg\"><path fill-rule=\"evenodd\" clip-rule=\"evenodd\" d=\"M16 10.554V37.4459L38.1463 24L16 10.554ZM12 8.77702C12 6.43812 14.5577 4.99881 16.5569 6.21266L41.6301 21.4356C43.5542 22.6038 43.5542 25.3962 41.6301 26.5644L16.5569 41.7873C14.5577 43.0012 12 41.5619 12 39.223V8.77702Z\"></path></svg><strong class=\"jsx-526152079 video-count\">6.4M</strong></div><div class=\"jsx-526152079\">6-23</div></div></div>","link":"https://www.tiktok.com/@bp_tiktok/video/6976919772369816834","retrieved":1629558382424},{"title":"","contents":"<div class=\"jsx-2261688415 _ratio_\"><div style=\"padding-top: 132.653%;\" class=\"jsx-2261688415\"><div class=\"jsx-2261688415 _ratio_wrapper\"><a href=\"https://www.tiktok.com/@bp_tiktok/video/6938644164917726465\" class=\"jsx-3808264675 video-feed-item-wrapper\"><span class=\"lazyload-wrapper\"><div style=\"height: 220px;\" class=\"lazyload-placeholder\"></div></span></a></div></div></div><div class=\"jsx-526152079 card-bottom-info\"><div class=\"meta-caption-line\"><h3 class=\"jsx-2276759325 video-meta-title\"><strong class=\"jsx-2276759325\">ROSÉ - ‘On The Ground’#</strong><a href=\"/tag/ros%C3%A9?lang=en\" class=\"tag-link jsx-231826672\" rel=\"noopener\"><strong class=\"jsx-231826672\">ROSÉ  </strong></a><strong class=\"jsx-2276759325\">#</strong><a href=\"/tag/%EB%A1%9C%EC%A0%9C?lang=en\" class=\"tag-link jsx-231826672\" rel=\"noopener\"><strong class=\"jsx-231826672\">로제  </strong></a><strong class=\"jsx-2276759325\">#</strong><a href=\"/tag/blackpink?lang=en\" class=\"tag-link jsx-231826672\" rel=\"noopener\"><strong class=\"jsx-231826672\">BLACKPINK  </strong></a><strong class=\"jsx-2276759325\">#</strong><a href=\"/tag/%EB%B8%94%EB%9E%99%ED%95%91%ED%81%AC?lang=en\" class=\"tag-link jsx-231826672\" rel=\"noopener\"><strong class=\"jsx-231826672\">블랙핑크  </strong></a><strong class=\"jsx-2276759325\">#</strong><a href=\"/tag/firstsinglealbum?lang=en\" class=\"tag-link jsx-231826672\" rel=\"noopener\"><strong class=\"jsx-231826672\">FirstSingleAlbum  </strong></a><strong class=\"jsx-2276759325\">#</strong><a href=\"/tag/ontheground?lang=en\" class=\"tag-link jsx-231826672\" rel=\"noopener\"><strong class=\"jsx-231826672\">OnTheGround  </strong></a><strong class=\"jsx-2276759325\">#</strong><a href=\"/tag/outnow?lang=en\" class=\"tag-link jsx-231826672\" rel=\"noopener\"><strong class=\"jsx-231826672\">OutNow  </strong></a><strong class=\"jsx-2276759325\">#</strong><a href=\"/tag/yg?lang=en\" class=\"tag-link jsx-231826672\" rel=\"noopener\"><strong class=\"jsx-231826672\">YG </strong></a></h3></div><div class=\"jsx-526152079 play-line\"><div class=\"jsx-526152079 play-icon\"><svg class=\"like-icon\" width=\"16\" height=\"16\" viewBox=\"0 0 48 48\" fill=\"rgba(22, 24, 35, 0.75)\" xmlns=\"http://www.w3.org/2000/svg\"><path fill-rule=\"evenodd\" clip-rule=\"evenodd\" d=\"M16 10.554V37.4459L38.1463 24L16 10.554ZM12 8.77702C12 6.43812 14.5577 4.99881 16.5569 6.21266L41.6301 21.4356C43.5542 22.6038 43.5542 25.3962 41.6301 26.5644L16.5569 41.7873C14.5577 43.0012 12 41.5619 12 39.223V8.77702Z\"></path></svg><strong class=\"jsx-526152079 video-count\">16M</strong></div><div class=\"jsx-526152079\">3-12</div></div></div>","link":"https://www.tiktok.com/@bp_tiktok/video/6938644164917726465","retrieved":1629558382536},{"title":"","contents":"<div class=\"jsx-2261688415 _ratio_\"><div style=\"padding-top: 132.653%;\" class=\"jsx-2261688415\"><div class=\"jsx-2261688415 _ratio_wrapper\"><a href=\"https://www.tiktok.com/@bp_tiktok/video/6937895465891466498\" class=\"jsx-3808264675 video-feed-item-wrapper\"><span class=\"lazyload-wrapper\"><div style=\"height: 220px;\" class=\"lazyload-placeholder\"></div></span></a></div></div></div><div class=\"jsx-526152079 card-bottom-info\"><div class=\"meta-caption-line\"><h3 class=\"jsx-2276759325 video-meta-title\"><strong class=\"jsx-2276759325\">ROSÉ - ‘On The Ground’ M/V TEASER </strong><a href=\"/tag/2?lang=en\" class=\"tag-link jsx-231826672\" rel=\"noopener\"><strong class=\"jsx-231826672\">#2 </strong></a><strong class=\"jsx-2276759325\">#R</strong><a href=\"/tag/ros%C3%A9?lang=en\" class=\"tag-link jsx-231826672\" rel=\"noopener\"><strong class=\"jsx-231826672\">OSÉ # </strong></a><strong class=\"jsx-2276759325\">로</strong><a href=\"/tag/%EB%A1%9C%EC%A0%9C?lang=en\" class=\"tag-link jsx-231826672\" rel=\"noopener\"><strong class=\"jsx-231826672\">제 # </strong></a><strong class=\"jsx-2276759325\">B</strong><a href=\"/tag/blackpink?lang=en\" class=\"tag-link jsx-231826672\" rel=\"noopener\"><strong class=\"jsx-231826672\">LACKPINK # </strong></a><strong class=\"jsx-2276759325\">블</strong><a href=\"/tag/%EB%B8%94%EB%9E%99%ED%95%91%ED%81%AC?lang=en\" class=\"tag-link jsx-231826672\" rel=\"noopener\"><strong class=\"jsx-231826672\">랙핑크 # </strong></a><strong class=\"jsx-2276759325\">F</strong><a href=\"/tag/firstsinglealbum?lang=en\" class=\"tag-link jsx-231826672\" rel=\"noopener\"><strong class=\"jsx-231826672\">irstSingleAlbum # </strong></a><strong class=\"jsx-2276759325\">O</strong><a href=\"/tag/ontheground?lang=en\" class=\"tag-link jsx-231826672\" rel=\"noopener\"><strong class=\"jsx-231826672\">nTheGround # </strong></a><strong class=\"jsx-2276759325\">M</strong><a href=\"/tag/mv_teaser?lang=en\" class=\"tag-link jsx-231826672\" rel=\"noopener\"><strong class=\"jsx-231826672\">V_Teaser # </strong></a><strong class=\"jsx-2276759325\">M</strong><a href=\"/tag/march12th?lang=en\" class=\"tag-link jsx-231826672\" rel=\"noopener\"><strong class=\"jsx-231826672\">arch12th # </strong></a><strong class=\"jsx-2276759325\">R</strong><a href=\"/tag/release?lang=en\" class=\"tag-link jsx-231826672\" rel=\"noopener\"><strong class=\"jsx-231826672\">ELEASE # </strong></a><strong class=\"jsx-2276759325\">Y</strong><a href=\"/tag/yg?lang=en\" class=\"tag-link jsx-231826672\" rel=\"noopener\"><strong class=\"jsx-231826672\">G </strong></a></h3></div><div class=\"jsx-526152079 play-line\"><div class=\"jsx-526152079 play-icon\"><svg class=\"like-icon\" width=\"16\" height=\"16\" viewBox=\"0 0 48 48\" fill=\"rgba(22, 24, 35, 0.75)\" xmlns=\"http://www.w3.org/2000/svg\"><path fill-rule=\"evenodd\" clip-rule=\"evenodd\" d=\"M16 10.554V37.4459L38.1463 24L16 10.554ZM12 8.77702C12 6.43812 14.5577 4.99881 16.5569 6.21266L41.6301 21.4356C43.5542 22.6038 43.5542 25.3962 41.6301 26.5644L16.5569 41.7873C14.5577 43.0012 12 41.5619 12 39.223V8.77702Z\"></path></svg><strong class=\"jsx-526152079 video-count\">8.9M</strong></div><div class=\"jsx-526152079\">3-10</div></div></div>","link":"https://www.tiktok.com/@bp_tiktok/video/6937895465891466498","retrieved":1629558382440},{"title":"","contents":"<div class=\"jsx-2261688415 _ratio_\"><div style=\"padding-top: 132.653%;\" class=\"jsx-2261688415\"><div class=\"jsx-2261688415 _ratio_wrapper\"><a href=\"https://www.tiktok.com/@bp_tiktok/video/6937144050856348929\" class=\"jsx-3808264675 video-feed-item-wrapper\"><span class=\"lazyload-wrapper\"><div style=\"height: 220px;\" class=\"lazyload-placeholder\"></div></span></a></div></div></div><div class=\"jsx-526152079 card-bottom-info\"><div class=\"meta-caption-line\"><h3 class=\"jsx-2276759325 video-meta-title\"><strong class=\"jsx-2276759325\">ROSÉ - ‘On The Ground’ M/V TEASER#</strong><a href=\"/tag/ros%C3%A9?lang=en\" class=\"tag-link jsx-231826672\" rel=\"noopener\"><strong class=\"jsx-231826672\">ROSÉ  </strong></a><strong class=\"jsx-2276759325\">#</strong><a href=\"/tag/%EB%A1%9C%EC%A0%9C?lang=en\" class=\"tag-link jsx-231826672\" rel=\"noopener\"><strong class=\"jsx-231826672\">로제  </strong></a><strong class=\"jsx-2276759325\">#</strong><a href=\"/tag/blackpink?lang=en\" class=\"tag-link jsx-231826672\" rel=\"noopener\"><strong class=\"jsx-231826672\">BLACKPINK  </strong></a><strong class=\"jsx-2276759325\">#</strong><a href=\"/tag/%EB%B8%94%EB%9E%99%ED%95%91%ED%81%AC?lang=en\" class=\"tag-link jsx-231826672\" rel=\"noopener\"><strong class=\"jsx-231826672\">블랙핑크  </strong></a><strong class=\"jsx-2276759325\">#</strong><a href=\"/tag/firstsinglealbum?lang=en\" class=\"tag-link jsx-231826672\" rel=\"noopener\"><strong class=\"jsx-231826672\">FirstSingleAlbum  </strong></a><strong class=\"jsx-2276759325\">#</strong><a href=\"/tag/r?lang=en\" class=\"tag-link jsx-231826672\" rel=\"noopener\"><strong class=\"jsx-231826672\">R  </strong></a><strong class=\"jsx-2276759325\">#</strong><a href=\"/tag/ontheground?lang=en\" class=\"tag-link jsx-231826672\" rel=\"noopener\"><strong class=\"jsx-231826672\">OnTheGround  </strong></a><strong class=\"jsx-2276759325\">#</strong><a href=\"/tag/mv_teaser?lang=en\" class=\"tag-link jsx-231826672\" rel=\"noopener\"><strong class=\"jsx-231826672\">MV_Teaser  </strong></a><strong class=\"jsx-2276759325\">#</strong><a href=\"/tag/20210312?lang=en\" class=\"tag-link jsx-231826672\" rel=\"noopener\"><strong class=\"jsx-231826672\">20210312  </strong></a><strong class=\"jsx-2276759325\">#</strong><a href=\"/tag/release?lang=en\" class=\"tag-link jsx-231826672\" rel=\"noopener\"><strong class=\"jsx-231826672\">RELEASE  </strong></a><strong class=\"jsx-2276759325\">#</strong><a href=\"/tag/yg?lang=en\" class=\"tag-link jsx-231826672\" rel=\"noopener\"><strong class=\"jsx-231826672\">YG </strong></a></h3></div><div class=\"jsx-526152079 play-line\"><div class=\"jsx-526152079 play-icon\"><svg class=\"like-icon\" width=\"16\" height=\"16\" viewBox=\"0 0 48 48\" fill=\"rgba(22, 24, 35, 0.75)\" xmlns=\"http://www.w3.org/2000/svg\"><path fill-rule=\"evenodd\" clip-rule=\"evenodd\" d=\"M16 10.554V37.4459L38.1463 24L16 10.554ZM12 8.77702C12 6.43812 14.5577 4.99881 16.5569 6.21266L41.6301 21.4356C43.5542 22.6038 43.5542 25.3962 41.6301 26.5644L16.5569 41.7873C14.5577 43.0012 12 41.5619 12 39.223V8.77702Z\"></path></svg><strong class=\"jsx-526152079 video-count\">9.1M</strong></div><div class=\"jsx-526152079\">3-8</div></div></div>","link":"https://www.tiktok.com/@bp_tiktok/video/6937144050856348929","retrieved":1629558382441},{"title":"","contents":"<div class=\"jsx-2261688415 _ratio_\"><div style=\"padding-top: 132.653%;\" class=\"jsx-2261688415\"><div class=\"jsx-2261688415 _ratio_wrapper\"><a href=\"https://www.tiktok.com/@bp_tiktok/video/6887155817536032002\" class=\"jsx-3808264675 video-feed-item-wrapper\"><span class=\"lazyload-wrapper\"><div style=\"height: 220px;\" class=\"lazyload-placeholder\"></div></span></a></div></div></div><div class=\"jsx-526152079 card-bottom-info\"><div class=\"meta-caption-line\"><h3 class=\"jsx-2276759325 video-meta-title\"><strong class=\"jsx-2276759325\">TikTok Stage with BLACKPINK rebroadcast with English subtitles will be LIVE on October 24th 7PM PT / 10PM ET </strong><a href=\"/@tiktok_stage?lang=en\" class=\"user-link jsx-231826672\" rel=\"noopener\"><strong class=\"jsx-231826672\">@tiktok_stage  </strong></a><strong class=\"jsx-2276759325\"> </strong><a href=\"/tag/tiktokstagewithblackpink?lang=en\" class=\"tag-link jsx-231826672\" rel=\"noopener\"><strong class=\"jsx-231826672\">#TikTokStageWithBLACKPINK </strong></a></h3></div><div class=\"jsx-526152079 play-line\"><div class=\"jsx-526152079 play-icon\"><svg class=\"like-icon\" width=\"16\" height=\"16\" viewBox=\"0 0 48 48\" fill=\"rgba(22, 24, 35, 0.75)\" xmlns=\"http://www.w3.org/2000/svg\"><path fill-rule=\"evenodd\" clip-rule=\"evenodd\" d=\"M16 10.554V37.4459L38.1463 24L16 10.554ZM12 8.77702C12 6.43812 14.5577 4.99881 16.5569 6.21266L41.6301 21.4356C43.5542 22.6038 43.5542 25.3962 41.6301 26.5644L16.5569 41.7873C14.5577 43.0012 12 41.5619 12 39.223V8.77702Z\"></path></svg><strong class=\"jsx-526152079 video-count\">10.3M</strong></div><div class=\"jsx-526152079\">2020-10-24</div></div></div>","link":"https://www.tiktok.com/@bp_tiktok/video/6887155817536032002","retrieved":1629558382442},{"title":"","contents":"<div class=\"jsx-2261688415 _ratio_\"><div style=\"padding-top: 132.653%;\" class=\"jsx-2261688415\"><div class=\"jsx-2261688415 _ratio_wrapper\"><a href=\"https://www.tiktok.com/@bp_tiktok/video/6884449540418620673\" class=\"jsx-3808264675 video-feed-item-wrapper\"><span class=\"lazyload-wrapper\"><div style=\"height: 220px;\" class=\"lazyload-placeholder\"></div></span></a></div></div></div><div class=\"jsx-526152079 card-bottom-info\"><div class=\"meta-caption-line\"><h3 class=\"jsx-2276759325 video-meta-title\"><a href=\"/@tiktok_stage?lang=en\" class=\"user-link jsx-231826672\" rel=\"noopener\"><strong class=\"jsx-231826672\">@tiktok_stage  </strong></a><strong class=\"jsx-2276759325\"> </strong><a href=\"/tag/tiktokstagewithblackpink?lang=en\" class=\"tag-link jsx-231826672\" rel=\"noopener\"><strong class=\"jsx-231826672\">#TikTokStageWithBLACKPINK </strong></a></h3></div><div class=\"jsx-526152079 play-line\"><div class=\"jsx-526152079 play-icon\"><svg class=\"like-icon\" width=\"16\" height=\"16\" viewBox=\"0 0 48 48\" fill=\"rgba(22, 24, 35, 0.75)\" xmlns=\"http://www.w3.org/2000/svg\"><path fill-rule=\"evenodd\" clip-rule=\"evenodd\" d=\"M16 10.554V37.4459L38.1463 24L16 10.554ZM12 8.77702C12 6.43812 14.5577 4.99881 16.5569 6.21266L41.6301 21.4356C43.5542 22.6038 43.5542 25.3962 41.6301 26.5644L16.5569 41.7873C14.5577 43.0012 12 41.5619 12 39.223V8.77702Z\"></path></svg><strong class=\"jsx-526152079 video-count\">15.4M</strong></div><div class=\"jsx-526152079\">2020-10-17</div></div></div>","link":"https://www.tiktok.com/@bp_tiktok/video/6884449540418620673","retrieved":1629558382471},{"title":"","contents":"<div class=\"jsx-2261688415 _ratio_\"><div style=\"padding-top: 132.653%;\" class=\"jsx-2261688415\"><div class=\"jsx-2261688415 _ratio_wrapper\"><a href=\"https://www.tiktok.com/@bp_tiktok/video/6884084456773258498\" class=\"jsx-3808264675 video-feed-item-wrapper\"><span class=\"lazyload-wrapper\"><div style=\"height: 220px;\" class=\"lazyload-placeholder\"></div></span></a></div></div></div><div class=\"jsx-526152079 card-bottom-info\"><div class=\"meta-caption-line\"><h3 class=\"jsx-2276759325 video-meta-title\"><a href=\"/@tiktok_stage?lang=en\" class=\"user-link jsx-231826672\" rel=\"noopener\"><strong class=\"jsx-231826672\">@tiktok_stage  </strong></a><strong class=\"jsx-2276759325\"> </strong><a href=\"/tag/tiktokstagewithblackpink?lang=en\" class=\"tag-link jsx-231826672\" rel=\"noopener\"><strong class=\"jsx-231826672\">#TikTokStageWithBLACKPINK </strong></a></h3></div><div class=\"jsx-526152079 play-line\"><div class=\"jsx-526152079 play-icon\"><svg class=\"like-icon\" width=\"16\" height=\"16\" viewBox=\"0 0 48 48\" fill=\"rgba(22, 24, 35, 0.75)\" xmlns=\"http://www.w3.org/2000/svg\"><path fill-rule=\"evenodd\" clip-rule=\"evenodd\" d=\"M16 10.554V37.4459L38.1463 24L16 10.554ZM12 8.77702C12 6.43812 14.5577 4.99881 16.5569 6.21266L41.6301 21.4356C43.5542 22.6038 43.5542 25.3962 41.6301 26.5644L16.5569 41.7873C14.5577 43.0012 12 41.5619 12 39.223V8.77702Z\"></path></svg><strong class=\"jsx-526152079 video-count\">12.5M</strong></div><div class=\"jsx-526152079\">2020-10-16</div></div></div>","link":"https://www.tiktok.com/@bp_tiktok/video/6884084456773258498","retrieved":1629558382471},{"title":"","contents":"<div class=\"jsx-2261688415 _ratio_\"><div style=\"padding-top: 132.653%;\" class=\"jsx-2261688415\"><div class=\"jsx-2261688415 _ratio_wrapper\"><a href=\"https://www.tiktok.com/@bp_tiktok/video/6883414279920356609\" class=\"jsx-3808264675 video-feed-item-wrapper\"><span class=\"lazyload-wrapper\"><div style=\"height: 220px;\" class=\"lazyload-placeholder\"></div></span></a></div></div></div><div class=\"jsx-526152079 card-bottom-info\"><div class=\"meta-caption-line\"><h3 class=\"jsx-2276759325 video-meta-title\"><strong class=\"jsx-2276759325\">[‘TikTok Stage with BLACKPINK’ Teaser Video] </strong><a href=\"/@tiktok_stage?lang=en\" class=\"user-link jsx-231826672\" rel=\"noopener\"><strong class=\"jsx-231826672\">@tiktok_stage  </strong></a><strong class=\"jsx-2276759325\"> </strong><a href=\"/tag/blackpink?lang=en\" class=\"tag-link jsx-231826672\" rel=\"noopener\"><strong class=\"jsx-231826672\">#BLACKPINK </strong></a><strong class=\"jsx-2276759325\"> </strong><a href=\"/tag/tiktokstagewithblackpink?lang=en\" class=\"tag-link jsx-231826672\" rel=\"noopener\"><strong class=\"jsx-231826672\">#TikTokStageWithBLACKPINK </strong></a><strong class=\"jsx-2276759325\"> </strong><a href=\"/tag/tiktoklive?lang=en\" class=\"tag-link jsx-231826672\" rel=\"noopener\"><strong class=\"jsx-231826672\">#TikTokLive </strong></a><strong class=\"jsx-2276759325\"> </strong><a href=\"/tag/teaservideo?lang=en\" class=\"tag-link jsx-231826672\" rel=\"noopener\"><strong class=\"jsx-231826672\">#TeaserVideo </strong></a><strong class=\"jsx-2276759325\"> </strong><a href=\"/tag/20201021_7pmkst?lang=en\" class=\"tag-link jsx-231826672\" rel=\"noopener\"><strong class=\"jsx-231826672\">#20201021_7pmKST </strong></a><strong class=\"jsx-2276759325\"> </strong><a href=\"/tag/yg?lang=en\" class=\"tag-link jsx-231826672\" rel=\"noopener\"><strong class=\"jsx-231826672\">#YG </strong></a></h3></div><div class=\"jsx-526152079 play-line\"><div class=\"jsx-526152079 play-icon\"><svg class=\"like-icon\" width=\"16\" height=\"16\" viewBox=\"0 0 48 48\" fill=\"rgba(22, 24, 35, 0.75)\" xmlns=\"http://www.w3.org/2000/svg\"><path fill-rule=\"evenodd\" clip-rule=\"evenodd\" d=\"M16 10.554V37.4459L38.1463 24L16 10.554ZM12 8.77702C12 6.43812 14.5577 4.99881 16.5569 6.21266L41.6301 21.4356C43.5542 22.6038 43.5542 25.3962 41.6301 26.5644L16.5569 41.7873C14.5577 43.0012 12 41.5619 12 39.223V8.77702Z\"></path></svg><strong class=\"jsx-526152079 video-count\">11.8M</strong></div><div class=\"jsx-526152079\">2020-10-14</div></div></div>","link":"https://www.tiktok.com/@bp_tiktok/video/6883414279920356609","retrieved":1629558382474},{"title":"","contents":"<div class=\"jsx-2261688415 _ratio_\"><div style=\"padding-top: 132.653%;\" class=\"jsx-2261688415\"><div class=\"jsx-2261688415 _ratio_wrapper\"><a href=\"https://www.tiktok.com/@bp_tiktok/video/6883316568256761089\" class=\"jsx-3808264675 video-feed-item-wrapper\"><span class=\"lazyload-wrapper\"><div style=\"height: 220px;\" class=\"lazyload-placeholder\"></div></span></a></div></div></div><div class=\"jsx-526152079 card-bottom-info\"><div class=\"meta-caption-line\"><h3 class=\"jsx-2276759325 video-meta-title\"><strong class=\"jsx-2276759325\">@TikTok_stage with 🖤BLACKPINK💗 will be coming to you all LIVE! Please participate in challenge to win a chance to attend </strong><a href=\"/tag/tiktokstagewithblackpink?lang=en\" class=\"tag-link jsx-231826672\" rel=\"noopener\"><strong class=\"jsx-231826672\">#TikTokStageWithBLACKPINK </strong></a></h3></div><div class=\"jsx-526152079 play-line\"><div class=\"jsx-526152079 play-icon\"><svg class=\"like-icon\" width=\"16\" height=\"16\" viewBox=\"0 0 48 48\" fill=\"rgba(22, 24, 35, 0.75)\" xmlns=\"http://www.w3.org/2000/svg\"><path fill-rule=\"evenodd\" clip-rule=\"evenodd\" d=\"M16 10.554V37.4459L38.1463 24L16 10.554ZM12 8.77702C12 6.43812 14.5577 4.99881 16.5569 6.21266L41.6301 21.4356C43.5542 22.6038 43.5542 25.3962 41.6301 26.5644L16.5569 41.7873C14.5577 43.0012 12 41.5619 12 39.223V8.77702Z\"></path></svg><strong class=\"jsx-526152079 video-count\">10.3M</strong></div><div class=\"jsx-526152079\">2020-10-14</div></div></div>","link":"https://www.tiktok.com/@bp_tiktok/video/6883316568256761089","retrieved":1629558382474},{"title":"","contents":"<div class=\"jsx-2261688415 _ratio_\"><div style=\"padding-top: 132.653%;\" class=\"jsx-2261688415\"><div class=\"jsx-2261688415 _ratio_wrapper\"><a href=\"https://www.tiktok.com/@bp_tiktok/video/6878982588954987777\" class=\"jsx-3808264675 video-feed-item-wrapper\"><span class=\"lazyload-wrapper\"><div style=\"height: 220px;\" class=\"lazyload-placeholder\"></div></span></a></div></div></div><div class=\"jsx-526152079 card-bottom-info\"><div class=\"meta-caption-line\"><h3 class=\"jsx-2276759325 video-meta-title\"><strong class=\"jsx-2276759325\">‘THE ALBUM’ is OUT NOW! </strong><a href=\"/tag/lovesickgirls?lang=en\" class=\"tag-link jsx-231826672\" rel=\"noopener\"><strong class=\"jsx-231826672\">#LovesickGirls </strong></a><strong class=\"jsx-2276759325\"> on TikTok now 🖤💗</strong></h3></div><div class=\"jsx-526152079 play-line\"><div class=\"jsx-526152079 play-icon\"><svg class=\"like-icon\" width=\"16\" height=\"16\" viewBox=\"0 0 48 48\" fill=\"rgba(22, 24, 35, 0.75)\" xmlns=\"http://www.w3.org/2000/svg\"><path fill-rule=\"evenodd\" clip-rule=\"evenodd\" d=\"M16 10.554V37.4459L38.1463 24L16 10.554ZM12 8.77702C12 6.43812 14.5577 4.99881 16.5569 6.21266L41.6301 21.4356C43.5542 22.6038 43.5542 25.3962 41.6301 26.5644L16.5569 41.7873C14.5577 43.0012 12 41.5619 12 39.223V8.77702Z\"></path></svg><strong class=\"jsx-526152079 video-count\">18.3M</strong></div><div class=\"jsx-526152079\">2020-10-2</div></div></div>","link":"https://www.tiktok.com/@bp_tiktok/video/6878982588954987777","retrieved":1629558382474},{"title":"","contents":"<div class=\"jsx-2261688415 _ratio_\"><div style=\"padding-top: 132.653%;\" class=\"jsx-2261688415\"><div class=\"jsx-2261688415 _ratio_wrapper\"><a href=\"https://www.tiktok.com/@bp_tiktok/video/6872188279907798274\" class=\"jsx-3808264675 video-feed-item-wrapper\"><span class=\"lazyload-wrapper\"><div style=\"height: 220px;\" class=\"lazyload-placeholder\"></div></span></a></div></div></div><div class=\"jsx-526152079 card-bottom-info\"><div class=\"meta-caption-line\"><h3 class=\"jsx-2276759325 video-meta-title\"><strong class=\"jsx-2276759325\">Na na na na na 🎶 </strong><a href=\"/tag/icecream%F0%9F%8D%A6?lang=en\" class=\"tag-link jsx-231826672\" rel=\"noopener\"><strong class=\"jsx-231826672\">#icecream🍦 </strong></a></h3></div><div class=\"jsx-526152079 play-line\"><div class=\"jsx-526152079 play-icon\"><svg class=\"like-icon\" width=\"16\" height=\"16\" viewBox=\"0 0 48 48\" fill=\"rgba(22, 24, 35, 0.75)\" xmlns=\"http://www.w3.org/2000/svg\"><path fill-rule=\"evenodd\" clip-rule=\"evenodd\" d=\"M16 10.554V37.4459L38.1463 24L16 10.554ZM12 8.77702C12 6.43812 14.5577 4.99881 16.5569 6.21266L41.6301 21.4356C43.5542 22.6038 43.5542 25.3962 41.6301 26.5644L16.5569 41.7873C14.5577 43.0012 12 41.5619 12 39.223V8.77702Z\"></path></svg><strong class=\"jsx-526152079 video-count\">25.5M</strong></div><div class=\"jsx-526152079\">2020-9-14</div></div></div>","link":"https://www.tiktok.com/@bp_tiktok/video/6872188279907798274","retrieved":1629558382475},{"title":"","contents":"<div class=\"jsx-2261688415 _ratio_\"><div style=\"padding-top: 132.653%;\" class=\"jsx-2261688415\"><div class=\"jsx-2261688415 _ratio_wrapper\"><a href=\"https://www.tiktok.com/@bp_tiktok/video/6871817657042210050\" class=\"jsx-3808264675 video-feed-item-wrapper\"><span class=\"lazyload-wrapper\"><div style=\"height: 220px;\" class=\"lazyload-placeholder\"></div></span></a></div></div></div><div class=\"jsx-526152079 card-bottom-info\"><div class=\"meta-caption-line\"><h3 class=\"jsx-2276759325 video-meta-title\"><strong class=\"jsx-2276759325\">get it flip it scoop it </strong><a href=\"/tag/icecream?lang=en\" class=\"tag-link jsx-231826672\" rel=\"noopener\"><strong class=\"jsx-231826672\">#icecream </strong></a><strong class=\"jsx-2276759325\"> 🍦</strong></h3></div><div class=\"jsx-526152079 play-line\"><div class=\"jsx-526152079 play-icon\"><svg class=\"like-icon\" width=\"16\" height=\"16\" viewBox=\"0 0 48 48\" fill=\"rgba(22, 24, 35, 0.75)\" xmlns=\"http://www.w3.org/2000/svg\"><path fill-rule=\"evenodd\" clip-rule=\"evenodd\" d=\"M16 10.554V37.4459L38.1463 24L16 10.554ZM12 8.77702C12 6.43812 14.5577 4.99881 16.5569 6.21266L41.6301 21.4356C43.5542 22.6038 43.5542 25.3962 41.6301 26.5644L16.5569 41.7873C14.5577 43.0012 12 41.5619 12 39.223V8.77702Z\"></path></svg><strong class=\"jsx-526152079 video-count\">25.7M</strong></div><div class=\"jsx-526152079\">2020-9-13</div></div></div>","link":"https://www.tiktok.com/@bp_tiktok/video/6871817657042210050","retrieved":1629558382475},{"title":"","contents":"<div class=\"jsx-2261688415 _ratio_\"><div style=\"padding-top: 132.653%;\" class=\"jsx-2261688415\"><div class=\"jsx-2261688415 _ratio_wrapper\"><a href=\"https://www.tiktok.com/@bp_tiktok/video/6871446235757268226\" class=\"jsx-3808264675 video-feed-item-wrapper\"><span class=\"lazyload-wrapper\"><div style=\"height: 220px;\" class=\"lazyload-placeholder\"></div></span></a></div></div></div><div class=\"jsx-526152079 card-bottom-info\"><div class=\"meta-caption-line\"><h3 class=\"jsx-2276759325 video-meta-title\"><strong class=\"jsx-2276759325\">Cherry on top </strong><a href=\"/tag/icecream?lang=en\" class=\"tag-link jsx-231826672\" rel=\"noopener\"><strong class=\"jsx-231826672\">#icecream </strong></a><strong class=\"jsx-2276759325\"> 🍦</strong></h3></div><div class=\"jsx-526152079 play-line\"><div class=\"jsx-526152079 play-icon\"><svg class=\"like-icon\" width=\"16\" height=\"16\" viewBox=\"0 0 48 48\" fill=\"rgba(22, 24, 35, 0.75)\" xmlns=\"http://www.w3.org/2000/svg\"><path fill-rule=\"evenodd\" clip-rule=\"evenodd\" d=\"M16 10.554V37.4459L38.1463 24L16 10.554ZM12 8.77702C12 6.43812 14.5577 4.99881 16.5569 6.21266L41.6301 21.4356C43.5542 22.6038 43.5542 25.3962 41.6301 26.5644L16.5569 41.7873C14.5577 43.0012 12 41.5619 12 39.223V8.77702Z\"></path></svg><strong class=\"jsx-526152079 video-count\">21.7M</strong></div><div class=\"jsx-526152079\">2020-9-12</div></div></div>","link":"https://www.tiktok.com/@bp_tiktok/video/6871446235757268226","retrieved":1629558382476},{"title":"","contents":"<div class=\"jsx-2261688415 _ratio_\"><div style=\"padding-top: 132.653%;\" class=\"jsx-2261688415\"><div class=\"jsx-2261688415 _ratio_wrapper\"><a href=\"https://www.tiktok.com/@bp_tiktok/video/6871075002490309889\" class=\"jsx-3808264675 video-feed-item-wrapper\"><span class=\"lazyload-wrapper\"><div style=\"height: 220px;\" class=\"lazyload-placeholder\"></div></span></a></div></div></div><div class=\"jsx-526152079 card-bottom-info\"><div class=\"meta-caption-line\"><h3 class=\"jsx-2276759325 video-meta-title\"><strong class=\"jsx-2276759325\">So good so sweet </strong><a href=\"/tag/icecream?lang=en\" class=\"tag-link jsx-231826672\" rel=\"noopener\"><strong class=\"jsx-231826672\">#icecream </strong></a><strong class=\"jsx-2276759325\"> 🍦</strong></h3></div><div class=\"jsx-526152079 play-line\"><div class=\"jsx-526152079 play-icon\"><svg class=\"like-icon\" width=\"16\" height=\"16\" viewBox=\"0 0 48 48\" fill=\"rgba(22, 24, 35, 0.75)\" xmlns=\"http://www.w3.org/2000/svg\"><path fill-rule=\"evenodd\" clip-rule=\"evenodd\" d=\"M16 10.554V37.4459L38.1463 24L16 10.554ZM12 8.77702C12 6.43812 14.5577 4.99881 16.5569 6.21266L41.6301 21.4356C43.5542 22.6038 43.5542 25.3962 41.6301 26.5644L16.5569 41.7873C14.5577 43.0012 12 41.5619 12 39.223V8.77702Z\"></path></svg><strong class=\"jsx-526152079 video-count\">22.7M</strong></div><div class=\"jsx-526152079\">2020-9-11</div></div></div>","link":"https://www.tiktok.com/@bp_tiktok/video/6871075002490309889","retrieved":1629558382476},{"title":"","contents":"<div class=\"jsx-2261688415 _ratio_\"><div style=\"padding-top: 132.653%;\" class=\"jsx-2261688415\"><div class=\"jsx-2261688415 _ratio_wrapper\"><a href=\"https://www.tiktok.com/@bp_tiktok/video/6870708045844974850\" class=\"jsx-3808264675 video-feed-item-wrapper\"><span class=\"lazyload-wrapper\"><div style=\"height: 220px;\" class=\"lazyload-placeholder\"></div></span></a></div></div></div><div class=\"jsx-526152079 card-bottom-info\"><div class=\"meta-caption-line\"><h3 class=\"jsx-2276759325 video-meta-title\"><strong class=\"jsx-2276759325\">Ice cream chillin’ chillin’ </strong><a href=\"/tag/icecream?lang=en\" class=\"tag-link jsx-231826672\" rel=\"noopener\"><strong class=\"jsx-231826672\">#icecream </strong></a><strong class=\"jsx-2276759325\"> 🍦</strong></h3></div><div class=\"jsx-526152079 play-line\"><div class=\"jsx-526152079 play-icon\"><svg class=\"like-icon\" width=\"16\" height=\"16\" viewBox=\"0 0 48 48\" fill=\"rgba(22, 24, 35, 0.75)\" xmlns=\"http://www.w3.org/2000/svg\"><path fill-rule=\"evenodd\" clip-rule=\"evenodd\" d=\"M16 10.554V37.4459L38.1463 24L16 10.554ZM12 8.77702C12 6.43812 14.5577 4.99881 16.5569 6.21266L41.6301 21.4356C43.5542 22.6038 43.5542 25.3962 41.6301 26.5644L16.5569 41.7873C14.5577 43.0012 12 41.5619 12 39.223V8.77702Z\"></path></svg><strong class=\"jsx-526152079 video-count\">47.4M</strong></div><div class=\"jsx-526152079\">2020-9-10</div></div></div>","link":"https://www.tiktok.com/@bp_tiktok/video/6870708045844974850","retrieved":1629558382476},{"title":"","contents":"<div class=\"jsx-2261688415 _ratio_\"><div style=\"padding-top: 132.653%;\" class=\"jsx-2261688415\"><div class=\"jsx-2261688415 _ratio_wrapper\"><a href=\"https://www.tiktok.com/@bp_tiktok/video/6851153348964470018\" class=\"jsx-3808264675 video-feed-item-wrapper\"><span class=\"lazyload-wrapper\"><div style=\"height: 220px;\" class=\"lazyload-placeholder\"></div></span></a></div></div></div><div class=\"jsx-526152079 card-bottom-info\"><div class=\"meta-caption-line\"><h3 class=\"jsx-2276759325 video-meta-title\"><strong class=\"jsx-2276759325\">Doom doom challenge😂</strong></h3></div><div class=\"jsx-526152079 play-line\"><div class=\"jsx-526152079 play-icon\"><svg class=\"like-icon\" width=\"16\" height=\"16\" viewBox=\"0 0 48 48\" fill=\"rgba(22, 24, 35, 0.75)\" xmlns=\"http://www.w3.org/2000/svg\"><path fill-rule=\"evenodd\" clip-rule=\"evenodd\" d=\"M16 10.554V37.4459L38.1463 24L16 10.554ZM12 8.77702C12 6.43812 14.5577 4.99881 16.5569 6.21266L41.6301 21.4356C43.5542 22.6038 43.5542 25.3962 41.6301 26.5644L16.5569 41.7873C14.5577 43.0012 12 41.5619 12 39.223V8.77702Z\"></path></svg><strong class=\"jsx-526152079 video-count\">38.5M</strong></div><div class=\"jsx-526152079\">2020-7-19</div></div></div>","link":"https://www.tiktok.com/@bp_tiktok/video/6851153348964470018","retrieved":1629558382481},{"title":"","contents":"<div class=\"jsx-2261688415 _ratio_\"><div style=\"padding-top: 132.653%;\" class=\"jsx-2261688415\"><div class=\"jsx-2261688415 _ratio_wrapper\"><a href=\"https://www.tiktok.com/@bp_tiktok/video/6844097770438118657\" class=\"jsx-3808264675 video-feed-item-wrapper\"><span class=\"lazyload-wrapper\"><div style=\"height: 220px;\" class=\"lazyload-placeholder\"></div></span></a></div></div></div><div class=\"jsx-526152079 card-bottom-info\"><div class=\"music-line\"><a href=\"/music/How-You-Like-That-6842434423888037889?lang=en\" rel=\"noopener\"><svg class=\"music-icon\" width=\"16\" height=\"16\" viewBox=\"0 0 48 48\" fill=\"currentColor\" xmlns=\"http://www.w3.org/2000/svg\"><path fill-rule=\"evenodd\" clip-rule=\"evenodd\" d=\"M35.0001 10.7587C35.0001 10.1169 34.4041 9.64129 33.7784 9.78359L17.7902 13.4192C17.335 13.5227 17.0119 13.9275 17.0119 14.3943V37.9972H17.0109C17.0374 40.1644 14.8022 42.4189 11.612 43.2737C8.05093 44.2279 4.64847 43.0769 4.01236 40.7028C3.37624 38.3288 5.74735 35.6308 9.30838 34.6766C10.606 34.3289 11.8826 34.2608 13.0119 34.4294V14.3943C13.0119 12.0601 14.6271 10.0364 16.9033 9.5188L32.8914 5.88317C36.0204 5.17165 39.0001 7.54986 39.0001 10.7587V33.1191C39.084 35.3108 36.8331 37.6109 33.6032 38.4763C30.0421 39.4305 26.6397 38.2795 26.0036 35.9055C25.3675 33.5315 27.7386 30.8334 31.2996 29.8792C32.5961 29.5319 33.8715 29.4635 35.0001 29.6316V10.7587Z\"></path></svg>How You Like That - BLACKPINK</a></div><div class=\"jsx-526152079 play-line\"><div class=\"jsx-526152079 play-icon\"><svg class=\"like-icon\" width=\"16\" height=\"16\" viewBox=\"0 0 48 48\" fill=\"rgba(22, 24, 35, 0.75)\" xmlns=\"http://www.w3.org/2000/svg\"><path fill-rule=\"evenodd\" clip-rule=\"evenodd\" d=\"M16 10.554V37.4459L38.1463 24L16 10.554ZM12 8.77702C12 6.43812 14.5577 4.99881 16.5569 6.21266L41.6301 21.4356C43.5542 22.6038 43.5542 25.3962 41.6301 26.5644L16.5569 41.7873C14.5577 43.0012 12 41.5619 12 39.223V8.77702Z\"></path></svg><strong class=\"jsx-526152079 video-count\">42.6M</strong></div><div class=\"jsx-526152079\">2020-6-30</div></div></div>","link":"https://www.tiktok.com/@bp_tiktok/video/6844097770438118657","retrieved":1629558382481},{"title":"","contents":"<div class=\"jsx-2261688415 _ratio_\"><div style=\"padding-top: 132.653%;\" class=\"jsx-2261688415\"><div class=\"jsx-2261688415 _ratio_wrapper\"><a href=\"https://www.tiktok.com/@bp_tiktok/video/6844097265544498433\" class=\"jsx-3808264675 video-feed-item-wrapper\"><span class=\"lazyload-wrapper\"><div style=\"height: 220px;\" class=\"lazyload-placeholder\"></div></span></a></div></div></div><div class=\"jsx-526152079 card-bottom-info\"><div class=\"music-line\"><a href=\"/music/How-You-Like-That-6842434423888037889?lang=en\" rel=\"noopener\"><svg class=\"music-icon\" width=\"16\" height=\"16\" viewBox=\"0 0 48 48\" fill=\"currentColor\" xmlns=\"http://www.w3.org/2000/svg\"><path fill-rule=\"evenodd\" clip-rule=\"evenodd\" d=\"M35.0001 10.7587C35.0001 10.1169 34.4041 9.64129 33.7784 9.78359L17.7902 13.4192C17.335 13.5227 17.0119 13.9275 17.0119 14.3943V37.9972H17.0109C17.0374 40.1644 14.8022 42.4189 11.612 43.2737C8.05093 44.2279 4.64847 43.0769 4.01236 40.7028C3.37624 38.3288 5.74735 35.6308 9.30838 34.6766C10.606 34.3289 11.8826 34.2608 13.0119 34.4294V14.3943C13.0119 12.0601 14.6271 10.0364 16.9033 9.5188L32.8914 5.88317C36.0204 5.17165 39.0001 7.54986 39.0001 10.7587V33.1191C39.084 35.3108 36.8331 37.6109 33.6032 38.4763C30.0421 39.4305 26.6397 38.2795 26.0036 35.9055C25.3675 33.5315 27.7386 30.8334 31.2996 29.8792C32.5961 29.5319 33.8715 29.4635 35.0001 29.6316V10.7587Z\"></path></svg>How You Like That - BLACKPINK</a></div><div class=\"jsx-526152079 play-line\"><div class=\"jsx-526152079 play-icon\"><svg class=\"like-icon\" width=\"16\" height=\"16\" viewBox=\"0 0 48 48\" fill=\"rgba(22, 24, 35, 0.75)\" xmlns=\"http://www.w3.org/2000/svg\"><path fill-rule=\"evenodd\" clip-rule=\"evenodd\" d=\"M16 10.554V37.4459L38.1463 24L16 10.554ZM12 8.77702C12 6.43812 14.5577 4.99881 16.5569 6.21266L41.6301 21.4356C43.5542 22.6038 43.5542 25.3962 41.6301 26.5644L16.5569 41.7873C14.5577 43.0012 12 41.5619 12 39.223V8.77702Z\"></path></svg><strong class=\"jsx-526152079 video-count\">53M</strong></div><div class=\"jsx-526152079\">2020-6-30</div></div></div>","link":"https://www.tiktok.com/@bp_tiktok/video/6844097265544498433","retrieved":1629558382481},{"title":"","contents":"<div class=\"jsx-2261688415 _ratio_\"><div style=\"padding-top: 132.653%;\" class=\"jsx-2261688415\"><div class=\"jsx-2261688415 _ratio_wrapper\"><a href=\"https://www.tiktok.com/@bp_tiktok/video/6844095949795593473\" class=\"jsx-3808264675 video-feed-item-wrapper\"><span class=\"lazyload-wrapper\"><div style=\"height: 220px;\" class=\"lazyload-placeholder\"></div></span></a></div></div></div><div class=\"jsx-526152079 card-bottom-info\"><div class=\"music-line\"><a href=\"/music/How-You-Like-That-6842434423888037889?lang=en\" rel=\"noopener\"><svg class=\"music-icon\" width=\"16\" height=\"16\" viewBox=\"0 0 48 48\" fill=\"currentColor\" xmlns=\"http://www.w3.org/2000/svg\"><path fill-rule=\"evenodd\" clip-rule=\"evenodd\" d=\"M35.0001 10.7587C35.0001 10.1169 34.4041 9.64129 33.7784 9.78359L17.7902 13.4192C17.335 13.5227 17.0119 13.9275 17.0119 14.3943V37.9972H17.0109C17.0374 40.1644 14.8022 42.4189 11.612 43.2737C8.05093 44.2279 4.64847 43.0769 4.01236 40.7028C3.37624 38.3288 5.74735 35.6308 9.30838 34.6766C10.606 34.3289 11.8826 34.2608 13.0119 34.4294V14.3943C13.0119 12.0601 14.6271 10.0364 16.9033 9.5188L32.8914 5.88317C36.0204 5.17165 39.0001 7.54986 39.0001 10.7587V33.1191C39.084 35.3108 36.8331 37.6109 33.6032 38.4763C30.0421 39.4305 26.6397 38.2795 26.0036 35.9055C25.3675 33.5315 27.7386 30.8334 31.2996 29.8792C32.5961 29.5319 33.8715 29.4635 35.0001 29.6316V10.7587Z\"></path></svg>How You Like That - BLACKPINK</a></div><div class=\"jsx-526152079 play-line\"><div class=\"jsx-526152079 play-icon\"><svg class=\"like-icon\" width=\"16\" height=\"16\" viewBox=\"0 0 48 48\" fill=\"rgba(22, 24, 35, 0.75)\" xmlns=\"http://www.w3.org/2000/svg\"><path fill-rule=\"evenodd\" clip-rule=\"evenodd\" d=\"M16 10.554V37.4459L38.1463 24L16 10.554ZM12 8.77702C12 6.43812 14.5577 4.99881 16.5569 6.21266L41.6301 21.4356C43.5542 22.6038 43.5542 25.3962 41.6301 26.5644L16.5569 41.7873C14.5577 43.0012 12 41.5619 12 39.223V8.77702Z\"></path></svg><strong class=\"jsx-526152079 video-count\">32M</strong></div><div class=\"jsx-526152079\">2020-6-30</div></div></div>","link":"https://www.tiktok.com/@bp_tiktok/video/6844095949795593473","retrieved":1629558382483},{"title":"","contents":"<div class=\"jsx-2261688415 _ratio_\"><div style=\"padding-top: 132.653%;\" class=\"jsx-2261688415\"><div class=\"jsx-2261688415 _ratio_wrapper\"><a href=\"https://www.tiktok.com/@bp_tiktok/video/6844095692055645441\" class=\"jsx-3808264675 video-feed-item-wrapper\"><span class=\"lazyload-wrapper\"><div style=\"height: 220px;\" class=\"lazyload-placeholder\"></div></span></a></div></div></div><div class=\"jsx-526152079 card-bottom-info\"><div class=\"music-line\"><a href=\"/music/How-You-Like-That-6842434423888037889?lang=en\" rel=\"noopener\"><svg class=\"music-icon\" width=\"16\" height=\"16\" viewBox=\"0 0 48 48\" fill=\"currentColor\" xmlns=\"http://www.w3.org/2000/svg\"><path fill-rule=\"evenodd\" clip-rule=\"evenodd\" d=\"M35.0001 10.7587C35.0001 10.1169 34.4041 9.64129 33.7784 9.78359L17.7902 13.4192C17.335 13.5227 17.0119 13.9275 17.0119 14.3943V37.9972H17.0109C17.0374 40.1644 14.8022 42.4189 11.612 43.2737C8.05093 44.2279 4.64847 43.0769 4.01236 40.7028C3.37624 38.3288 5.74735 35.6308 9.30838 34.6766C10.606 34.3289 11.8826 34.2608 13.0119 34.4294V14.3943C13.0119 12.0601 14.6271 10.0364 16.9033 9.5188L32.8914 5.88317C36.0204 5.17165 39.0001 7.54986 39.0001 10.7587V33.1191C39.084 35.3108 36.8331 37.6109 33.6032 38.4763C30.0421 39.4305 26.6397 38.2795 26.0036 35.9055C25.3675 33.5315 27.7386 30.8334 31.2996 29.8792C32.5961 29.5319 33.8715 29.4635 35.0001 29.6316V10.7587Z\"></path></svg>How You Like That - BLACKPINK</a></div><div class=\"jsx-526152079 play-line\"><div class=\"jsx-526152079 play-icon\"><svg class=\"like-icon\" width=\"16\" height=\"16\" viewBox=\"0 0 48 48\" fill=\"rgba(22, 24, 35, 0.75)\" xmlns=\"http://www.w3.org/2000/svg\"><path fill-rule=\"evenodd\" clip-rule=\"evenodd\" d=\"M16 10.554V37.4459L38.1463 24L16 10.554ZM12 8.77702C12 6.43812 14.5577 4.99881 16.5569 6.21266L41.6301 21.4356C43.5542 22.6038 43.5542 25.3962 41.6301 26.5644L16.5569 41.7873C14.5577 43.0012 12 41.5619 12 39.223V8.77702Z\"></path></svg><strong class=\"jsx-526152079 video-count\">34.9M</strong></div><div class=\"jsx-526152079\">2020-6-30</div></div></div>","link":"https://www.tiktok.com/@bp_tiktok/video/6844095692055645441","retrieved":1629558382484},{"title":"","contents":"<div class=\"jsx-2261688415 _ratio_\"><div style=\"padding-top: 132.653%;\" class=\"jsx-2261688415\"><div class=\"jsx-2261688415 _ratio_wrapper\"><a href=\"https://www.tiktok.com/@bp_tiktok/video/6843659188183289089\" class=\"jsx-3808264675 video-feed-item-wrapper\"><span class=\"lazyload-wrapper\"><div style=\"height: 220px;\" class=\"lazyload-placeholder\"></div></span></a></div></div></div><div class=\"jsx-526152079 card-bottom-info\"><div class=\"music-line\"><a href=\"/music/How-You-Like-That-6842582526297393154?lang=en\" rel=\"noopener\"><svg class=\"music-icon\" width=\"16\" height=\"16\" viewBox=\"0 0 48 48\" fill=\"currentColor\" xmlns=\"http://www.w3.org/2000/svg\"><path fill-rule=\"evenodd\" clip-rule=\"evenodd\" d=\"M35.0001 10.7587C35.0001 10.1169 34.4041 9.64129 33.7784 9.78359L17.7902 13.4192C17.335 13.5227 17.0119 13.9275 17.0119 14.3943V37.9972H17.0109C17.0374 40.1644 14.8022 42.4189 11.612 43.2737C8.05093 44.2279 4.64847 43.0769 4.01236 40.7028C3.37624 38.3288 5.74735 35.6308 9.30838 34.6766C10.606 34.3289 11.8826 34.2608 13.0119 34.4294V14.3943C13.0119 12.0601 14.6271 10.0364 16.9033 9.5188L32.8914 5.88317C36.0204 5.17165 39.0001 7.54986 39.0001 10.7587V33.1191C39.084 35.3108 36.8331 37.6109 33.6032 38.4763C30.0421 39.4305 26.6397 38.2795 26.0036 35.9055C25.3675 33.5315 27.7386 30.8334 31.2996 29.8792C32.5961 29.5319 33.8715 29.4635 35.0001 29.6316V10.7587Z\"></path></svg>How You Like That - BLACKPINK</a></div><div class=\"jsx-526152079 play-line\"><div class=\"jsx-526152079 play-icon\"><svg class=\"like-icon\" width=\"16\" height=\"16\" viewBox=\"0 0 48 48\" fill=\"rgba(22, 24, 35, 0.75)\" xmlns=\"http://www.w3.org/2000/svg\"><path fill-rule=\"evenodd\" clip-rule=\"evenodd\" d=\"M16 10.554V37.4459L38.1463 24L16 10.554ZM12 8.77702C12 6.43812 14.5577 4.99881 16.5569 6.21266L41.6301 21.4356C43.5542 22.6038 43.5542 25.3962 41.6301 26.5644L16.5569 41.7873C14.5577 43.0012 12 41.5619 12 39.223V8.77702Z\"></path></svg><strong class=\"jsx-526152079 video-count\">22.1M</strong></div><div class=\"jsx-526152079\">2020-6-29</div></div></div>","link":"https://www.tiktok.com/@bp_tiktok/video/6843659188183289089","retrieved":1629558382486},{"title":"","contents":"<div class=\"jsx-2261688415 _ratio_\"><div style=\"padding-top: 132.653%;\" class=\"jsx-2261688415\"><div class=\"jsx-2261688415 _ratio_wrapper\"><a href=\"https://www.tiktok.com/@bp_tiktok/video/6842689884700921090\" class=\"jsx-3808264675 video-feed-item-wrapper\"><span class=\"lazyload-wrapper\"><div style=\"height: 220px;\" class=\"lazyload-placeholder\"></div></span></a></div></div></div><div class=\"jsx-526152079 card-bottom-info\"><div class=\"meta-caption-line\"><h3 class=\"jsx-2276759325 video-meta-title\"><a href=\"/tag/blackpink?lang=en\" class=\"tag-link jsx-231826672\" rel=\"noopener\"><strong class=\"jsx-231826672\">#BLACKPINK </strong></a><strong class=\"jsx-2276759325\"> </strong><a href=\"/tag/howyoulikethat?lang=en\" class=\"tag-link jsx-231826672\" rel=\"noopener\"><strong class=\"jsx-231826672\">#HOWYOULIKETHAT </strong></a><strong class=\"jsx-2276759325\"> NOW ON TIKTOK 💗</strong></h3></div><div class=\"jsx-526152079 play-line\"><div class=\"jsx-526152079 play-icon\"><svg class=\"like-icon\" width=\"16\" height=\"16\" viewBox=\"0 0 48 48\" fill=\"rgba(22, 24, 35, 0.75)\" xmlns=\"http://www.w3.org/2000/svg\"><path fill-rule=\"evenodd\" clip-rule=\"evenodd\" d=\"M16 10.554V37.4459L38.1463 24L16 10.554ZM12 8.77702C12 6.43812 14.5577 4.99881 16.5569 6.21266L41.6301 21.4356C43.5542 22.6038 43.5542 25.3962 41.6301 26.5644L16.5569 41.7873C14.5577 43.0012 12 41.5619 12 39.223V8.77702Z\"></path></svg><strong class=\"jsx-526152079 video-count\">72.4M</strong></div><div class=\"jsx-526152079\">2020-6-26</div></div></div>","link":"https://www.tiktok.com/@bp_tiktok/video/6842689884700921090","retrieved":1629558382487},{"title":"","contents":"<div class=\"jsx-2261688415 _ratio_\"><div style=\"padding-top: 132.653%;\" class=\"jsx-2261688415\"><div class=\"jsx-2261688415 _ratio_wrapper\"><a href=\"https://www.tiktok.com/@bp_tiktok/video/6842684361028996354\" class=\"jsx-3808264675 video-feed-item-wrapper\"><span class=\"lazyload-wrapper\"><div style=\"height: 220px;\" class=\"lazyload-placeholder\"></div></span></a></div></div></div><div class=\"jsx-526152079 card-bottom-info\"><div class=\"meta-caption-line\"><h3 class=\"jsx-2276759325 video-meta-title\"><a href=\"/tag/blackpink?lang=en\" class=\"tag-link jsx-231826672\" rel=\"noopener\"><strong class=\"jsx-231826672\">#BLACKPINK </strong></a><strong class=\"jsx-2276759325\"> </strong><a href=\"/tag/howyoulikethat?lang=en\" class=\"tag-link jsx-231826672\" rel=\"noopener\"><strong class=\"jsx-231826672\">#HowYouLikeThat </strong></a><strong class=\"jsx-2276759325\"> OUT NOW💗 https://youtu.be/ioNng23DkIM</strong></h3></div><div class=\"jsx-526152079 play-line\"><div class=\"jsx-526152079 play-icon\"><svg class=\"like-icon\" width=\"16\" height=\"16\" viewBox=\"0 0 48 48\" fill=\"rgba(22, 24, 35, 0.75)\" xmlns=\"http://www.w3.org/2000/svg\"><path fill-rule=\"evenodd\" clip-rule=\"evenodd\" d=\"M16 10.554V37.4459L38.1463 24L16 10.554ZM12 8.77702C12 6.43812 14.5577 4.99881 16.5569 6.21266L41.6301 21.4356C43.5542 22.6038 43.5542 25.3962 41.6301 26.5644L16.5569 41.7873C14.5577 43.0012 12 41.5619 12 39.223V8.77702Z\"></path></svg><strong class=\"jsx-526152079 video-count\">16.4M</strong></div><div class=\"jsx-526152079\">2020-6-26</div></div></div>","link":"https://www.tiktok.com/@bp_tiktok/video/6842684361028996354","retrieved":1629558382491},{"title":"","contents":"<div class=\"jsx-2261688415 _ratio_\"><div style=\"padding-top: 132.653%;\" class=\"jsx-2261688415\"><div class=\"jsx-2261688415 _ratio_wrapper\"><a href=\"https://www.tiktok.com/@bp_tiktok/video/6842289043363859714\" class=\"jsx-3808264675 video-feed-item-wrapper\"><span class=\"lazyload-wrapper\"><div style=\"height: 220px;\" class=\"lazyload-placeholder\"></div></span></a></div></div></div><div class=\"jsx-526152079 card-bottom-info\"><div class=\"meta-caption-line\"><h3 class=\"jsx-2276759325 video-meta-title\"><a href=\"/tag/blackpink?lang=en\" class=\"tag-link jsx-231826672\" rel=\"noopener\"><strong class=\"jsx-231826672\">#BLACKPINK </strong></a><strong class=\"jsx-2276759325\"> </strong><a href=\"/tag/howyoulikethat?lang=en\" class=\"tag-link jsx-231826672\" rel=\"noopener\"><strong class=\"jsx-231826672\">#HowYouLikeThat </strong></a><strong class=\"jsx-2276759325\"> M/V Teaser </strong><a href=\"/tag/20200626_6pm?lang=en\" class=\"tag-link jsx-231826672\" rel=\"noopener\"><strong class=\"jsx-231826672\">#20200626_6pm </strong></a><strong class=\"jsx-2276759325\"> </strong><a href=\"/tag/yg?lang=en\" class=\"tag-link jsx-231826672\" rel=\"noopener\"><strong class=\"jsx-231826672\">#YG </strong></a></h3></div><div class=\"jsx-526152079 play-line\"><div class=\"jsx-526152079 play-icon\"><svg class=\"like-icon\" width=\"16\" height=\"16\" viewBox=\"0 0 48 48\" fill=\"rgba(22, 24, 35, 0.75)\" xmlns=\"http://www.w3.org/2000/svg\"><path fill-rule=\"evenodd\" clip-rule=\"evenodd\" d=\"M16 10.554V37.4459L38.1463 24L16 10.554ZM12 8.77702C12 6.43812 14.5577 4.99881 16.5569 6.21266L41.6301 21.4356C43.5542 22.6038 43.5542 25.3962 41.6301 26.5644L16.5569 41.7873C14.5577 43.0012 12 41.5619 12 39.223V8.77702Z\"></path></svg><strong class=\"jsx-526152079 video-count\">14M</strong></div><div class=\"jsx-526152079\">2020-6-25</div></div></div>","link":"https://www.tiktok.com/@bp_tiktok/video/6842289043363859714","retrieved":1629558382492},{"title":"","contents":"<div class=\"jsx-2261688415 _ratio_\"><div style=\"padding-top: 132.653%;\" class=\"jsx-2261688415\"><div class=\"jsx-2261688415 _ratio_wrapper\"><a href=\"https://www.tiktok.com/@bp_tiktok/video/6841425328829631746\" class=\"jsx-3808264675 video-feed-item-wrapper\"><span class=\"lazyload-wrapper\"><div style=\"height: 220px;\" class=\"lazyload-placeholder\"></div></span></a></div></div></div><div class=\"jsx-526152079 card-bottom-info\"><div class=\"meta-caption-line\"><h3 class=\"jsx-2276759325 video-meta-title\"><a href=\"/tag/blackpink?lang=en\" class=\"tag-link jsx-231826672\" rel=\"noopener\"><strong class=\"jsx-231826672\">#BLACKPINK </strong></a><strong class=\"jsx-2276759325\"> 'How You Like That' JISOO Concept Teaser Video  Pre-Release Single✅2020.06.26 6PM#HowY</strong><a href=\"/tag/howyoulikethat?lang=en\" class=\"tag-link jsx-231826672\" rel=\"noopener\"><strong class=\"jsx-231826672\">ouLikeThat #JIS </strong></a><strong class=\"jsx-2276759325\">O</strong><a href=\"/tag/jisoo?lang=en\" class=\"tag-link jsx-231826672\" rel=\"noopener\"><strong class=\"jsx-231826672\">O #YG </strong></a><a href=\"/tag/yg?lang=en\" class=\"tag-link jsx-231826672\" rel=\"noopener\"><strong class=\"jsx-231826672\"> </strong></a></h3></div><div class=\"jsx-526152079 play-line\"><div class=\"jsx-526152079 play-icon\"><svg class=\"like-icon\" width=\"16\" height=\"16\" viewBox=\"0 0 48 48\" fill=\"rgba(22, 24, 35, 0.75)\" xmlns=\"http://www.w3.org/2000/svg\"><path fill-rule=\"evenodd\" clip-rule=\"evenodd\" d=\"M16 10.554V37.4459L38.1463 24L16 10.554ZM12 8.77702C12 6.43812 14.5577 4.99881 16.5569 6.21266L41.6301 21.4356C43.5542 22.6038 43.5542 25.3962 41.6301 26.5644L16.5569 41.7873C14.5577 43.0012 12 41.5619 12 39.223V8.77702Z\"></path></svg><strong class=\"jsx-526152079 video-count\">20.1M</strong></div><div class=\"jsx-526152079\">2020-6-23</div></div></div>","link":"https://www.tiktok.com/@bp_tiktok/video/6841425328829631746","retrieved":1629558382492},{"title":"","contents":"<div class=\"jsx-2261688415 _ratio_\"><div style=\"padding-top: 132.653%;\" class=\"jsx-2261688415\"><div class=\"jsx-2261688415 _ratio_wrapper\"><a href=\"https://www.tiktok.com/@bp_tiktok/video/6841425215256317186\" class=\"jsx-3808264675 video-feed-item-wrapper\"><span class=\"lazyload-wrapper\"><div style=\"height: 220px;\" class=\"lazyload-placeholder\"></div></span></a></div></div></div><div class=\"jsx-526152079 card-bottom-info\"><div class=\"meta-caption-line\"><h3 class=\"jsx-2276759325 video-meta-title\"><a href=\"/tag/blackpink?lang=en\" class=\"tag-link jsx-231826672\" rel=\"noopener\"><strong class=\"jsx-231826672\">#BLACKPINK </strong></a><strong class=\"jsx-2276759325\"> 'How You Like That' LISA Concept Teaser Video  Pre-Release Single✅2020.06.26 6PM#HowY</strong><a href=\"/tag/howyoulikethat?lang=en\" class=\"tag-link jsx-231826672\" rel=\"noopener\"><strong class=\"jsx-231826672\">ouLikeThat #LIS </strong></a><strong class=\"jsx-2276759325\">A</strong><a href=\"/tag/lisa?lang=en\" class=\"tag-link jsx-231826672\" rel=\"noopener\"><strong class=\"jsx-231826672\"> #YG </strong></a><a href=\"/tag/yg?lang=en\" class=\"tag-link jsx-231826672\" rel=\"noopener\"><strong class=\"jsx-231826672\"> </strong></a></h3></div><div class=\"jsx-526152079 play-line\"><div class=\"jsx-526152079 play-icon\"><svg class=\"like-icon\" width=\"16\" height=\"16\" viewBox=\"0 0 48 48\" fill=\"rgba(22, 24, 35, 0.75)\" xmlns=\"http://www.w3.org/2000/svg\"><path fill-rule=\"evenodd\" clip-rule=\"evenodd\" d=\"M16 10.554V37.4459L38.1463 24L16 10.554ZM12 8.77702C12 6.43812 14.5577 4.99881 16.5569 6.21266L41.6301 21.4356C43.5542 22.6038 43.5542 25.3962 41.6301 26.5644L16.5569 41.7873C14.5577 43.0012 12 41.5619 12 39.223V8.77702Z\"></path></svg><strong class=\"jsx-526152079 video-count\">22M</strong></div><div class=\"jsx-526152079\">2020-6-23</div></div></div>","link":"https://www.tiktok.com/@bp_tiktok/video/6841425215256317186","retrieved":1629558382492},{"title":"","contents":"<div class=\"jsx-2261688415 _ratio_\"><div style=\"padding-top: 132.653%;\" class=\"jsx-2261688415\"><div class=\"jsx-2261688415 _ratio_wrapper\"><a href=\"https://www.tiktok.com/@bp_tiktok/video/6841424937975057665\" class=\"jsx-3808264675 video-feed-item-wrapper\"><span class=\"lazyload-wrapper\"><div style=\"height: 220px;\" class=\"lazyload-placeholder\"></div></span></a></div></div></div><div class=\"jsx-526152079 card-bottom-info\"><div class=\"meta-caption-line\"><h3 class=\"jsx-2276759325 video-meta-title\"><a href=\"/tag/blackpink?lang=en\" class=\"tag-link jsx-231826672\" rel=\"noopener\"><strong class=\"jsx-231826672\">#BLACKPINK </strong></a><strong class=\"jsx-2276759325\"> 'How You Like That' JENNIE Concept Teaser Video  Pre-Release Single✅2020.06.26 6PM#HowY</strong><a href=\"/tag/howyoulikethat?lang=en\" class=\"tag-link jsx-231826672\" rel=\"noopener\"><strong class=\"jsx-231826672\">ouLikeThat #JEN </strong></a><strong class=\"jsx-2276759325\">N</strong><a href=\"/tag/jennie?lang=en\" class=\"tag-link jsx-231826672\" rel=\"noopener\"><strong class=\"jsx-231826672\">IE #YG </strong></a><a href=\"/tag/yg?lang=en\" class=\"tag-link jsx-231826672\" rel=\"noopener\"><strong class=\"jsx-231826672\"> </strong></a></h3></div><div class=\"jsx-526152079 play-line\"><div class=\"jsx-526152079 play-icon\"><svg class=\"like-icon\" width=\"16\" height=\"16\" viewBox=\"0 0 48 48\" fill=\"rgba(22, 24, 35, 0.75)\" xmlns=\"http://www.w3.org/2000/svg\"><path fill-rule=\"evenodd\" clip-rule=\"evenodd\" d=\"M16 10.554V37.4459L38.1463 24L16 10.554ZM12 8.77702C12 6.43812 14.5577 4.99881 16.5569 6.21266L41.6301 21.4356C43.5542 22.6038 43.5542 25.3962 41.6301 26.5644L16.5569 41.7873C14.5577 43.0012 12 41.5619 12 39.223V8.77702Z\"></path></svg><strong class=\"jsx-526152079 video-count\">26.7M</strong></div><div class=\"jsx-526152079\">2020-6-23</div></div></div>","link":"https://www.tiktok.com/@bp_tiktok/video/6841424937975057665","retrieved":1629558382493},{"title":"","contents":"<div class=\"jsx-2261688415 _ratio_\"><div style=\"padding-top: 132.653%;\" class=\"jsx-2261688415\"><div class=\"jsx-2261688415 _ratio_wrapper\"><a href=\"https://www.tiktok.com/@bp_tiktok/video/6841424768881708290\" class=\"jsx-3808264675 video-feed-item-wrapper\"><span class=\"lazyload-wrapper\"><div style=\"height: 220px;\" class=\"lazyload-placeholder\"></div></span></a></div></div></div><div class=\"jsx-526152079 card-bottom-info\"><div class=\"meta-caption-line\"><h3 class=\"jsx-2276759325 video-meta-title\"><a href=\"/tag/blackpink?lang=en\" class=\"tag-link jsx-231826672\" rel=\"noopener\"><strong class=\"jsx-231826672\">#BLACKPINK </strong></a><strong class=\"jsx-2276759325\"> 'How You Like That' ROSÉ Concept Teaser Video  Pre-Release Single✅2020.06.26 6PM#HowY</strong><a href=\"/tag/howyoulikethat?lang=en\" class=\"tag-link jsx-231826672\" rel=\"noopener\"><strong class=\"jsx-231826672\">ouLikeThat #ROS </strong></a><strong class=\"jsx-2276759325\">É</strong><a href=\"/tag/ros%C3%A9?lang=en\" class=\"tag-link jsx-231826672\" rel=\"noopener\"><strong class=\"jsx-231826672\"> #YG </strong></a><a href=\"/tag/yg?lang=en\" class=\"tag-link jsx-231826672\" rel=\"noopener\"><strong class=\"jsx-231826672\"> </strong></a></h3></div><div class=\"jsx-526152079 play-line\"><div class=\"jsx-526152079 play-icon\"><svg class=\"like-icon\" width=\"16\" height=\"16\" viewBox=\"0 0 48 48\" fill=\"rgba(22, 24, 35, 0.75)\" xmlns=\"http://www.w3.org/2000/svg\"><path fill-rule=\"evenodd\" clip-rule=\"evenodd\" d=\"M16 10.554V37.4459L38.1463 24L16 10.554ZM12 8.77702C12 6.43812 14.5577 4.99881 16.5569 6.21266L41.6301 21.4356C43.5542 22.6038 43.5542 25.3962 41.6301 26.5644L16.5569 41.7873C14.5577 43.0012 12 41.5619 12 39.223V8.77702Z\"></path></svg><strong class=\"jsx-526152079 video-count\">14.9M</strong></div><div class=\"jsx-526152079\">2020-6-23</div></div></div>","link":"https://www.tiktok.com/@bp_tiktok/video/6841424768881708290","retrieved":1629558382493},{"title":"","contents":"<div class=\"jsx-2261688415 _ratio_\"><div style=\"padding-top: 132.653%;\" class=\"jsx-2261688415\"><div class=\"jsx-2261688415 _ratio_wrapper\"><a href=\"https://www.tiktok.com/@bp_tiktok/video/6780139936659082497\" class=\"jsx-3808264675 video-feed-item-wrapper\"><span class=\"lazyload-wrapper\"><div style=\"height: 220px;\" class=\"lazyload-placeholder\"></div></span></a></div></div></div><div class=\"jsx-526152079 card-bottom-info\"><div class=\"meta-caption-line\"><h3 class=\"jsx-2276759325 video-meta-title\"><strong class=\"jsx-2276759325\">Come </strong><a href=\"/tag/danceawesome?lang=en\" class=\"tag-link jsx-231826672\" rel=\"noopener\"><strong class=\"jsx-231826672\">#danceAwesome </strong></a><strong class=\"jsx-2276759325\"> with us!🥰 </strong><a href=\"/@samsung?lang=en\" class=\"user-link jsx-231826672\" rel=\"noopener\"><strong class=\"jsx-231826672\">@samsung  </strong></a><strong class=\"jsx-2276759325\"> </strong><a href=\"/tag/galaxya?lang=en\" class=\"tag-link jsx-231826672\" rel=\"noopener\"><strong class=\"jsx-231826672\">#GalaxyA </strong></a><strong class=\"jsx-2276759325\"> </strong><a href=\"/tag/ad?lang=en\" class=\"tag-link jsx-231826672\" rel=\"noopener\"><strong class=\"jsx-231826672\">#Ad </strong></a></h3></div><div class=\"jsx-526152079 play-line\"><div class=\"jsx-526152079 play-icon\"><svg class=\"like-icon\" width=\"16\" height=\"16\" viewBox=\"0 0 48 48\" fill=\"rgba(22, 24, 35, 0.75)\" xmlns=\"http://www.w3.org/2000/svg\"><path fill-rule=\"evenodd\" clip-rule=\"evenodd\" d=\"M16 10.554V37.4459L38.1463 24L16 10.554ZM12 8.77702C12 6.43812 14.5577 4.99881 16.5569 6.21266L41.6301 21.4356C43.5542 22.6038 43.5542 25.3962 41.6301 26.5644L16.5569 41.7873C14.5577 43.0012 12 41.5619 12 39.223V8.77702Z\"></path></svg><strong class=\"jsx-526152079 video-count\">85.3M</strong></div><div class=\"jsx-526152079\">2020-1-10</div></div></div>","link":"https://www.tiktok.com/@bp_tiktok/video/6780139936659082497","retrieved":1629558382502},{"title":"","contents":"<div class=\"jsx-2261688415 _ratio_\"><div style=\"padding-top: 132.653%;\" class=\"jsx-2261688415\"><div class=\"jsx-2261688415 _ratio_wrapper\"><a href=\"https://www.tiktok.com/@bp_tiktok/video/6780139715078147329\" class=\"jsx-3808264675 video-feed-item-wrapper\"><span class=\"lazyload-wrapper\"><div style=\"height: 220px;\" class=\"lazyload-placeholder\"></div></span></a></div></div></div><div class=\"jsx-526152079 card-bottom-info\"><div class=\"meta-caption-line\"><h3 class=\"jsx-2276759325 video-meta-title\"><strong class=\"jsx-2276759325\">BLACKPINK in your area!🔥</strong><a href=\"/tag/danceawesome?lang=en\" class=\"tag-link jsx-231826672\" rel=\"noopener\"><strong class=\"jsx-231826672\">#danceAwesome </strong></a><strong class=\"jsx-2276759325\"> </strong><a href=\"/@samsung?lang=en\" class=\"user-link jsx-231826672\" rel=\"noopener\"><strong class=\"jsx-231826672\">@samsung  </strong></a><strong class=\"jsx-2276759325\">  </strong><a href=\"/tag/galaxya?lang=en\" class=\"tag-link jsx-231826672\" rel=\"noopener\"><strong class=\"jsx-231826672\">#GalaxyA </strong></a></h3></div><div class=\"jsx-526152079 play-line\"><div class=\"jsx-526152079 play-icon\"><svg class=\"like-icon\" width=\"16\" height=\"16\" viewBox=\"0 0 48 48\" fill=\"rgba(22, 24, 35, 0.75)\" xmlns=\"http://www.w3.org/2000/svg\"><path fill-rule=\"evenodd\" clip-rule=\"evenodd\" d=\"M16 10.554V37.4459L38.1463 24L16 10.554ZM12 8.77702C12 6.43812 14.5577 4.99881 16.5569 6.21266L41.6301 21.4356C43.5542 22.6038 43.5542 25.3962 41.6301 26.5644L16.5569 41.7873C14.5577 43.0012 12 41.5619 12 39.223V8.77702Z\"></path></svg><strong class=\"jsx-526152079 video-count\">16.9M</strong></div><div class=\"jsx-526152079\">2020-1-10</div></div></div>","link":"https://www.tiktok.com/@bp_tiktok/video/6780139715078147329","retrieved":1629558382502},{"title":"","contents":"<div class=\"jsx-2261688415 _ratio_\"><div style=\"padding-top: 132.653%;\" class=\"jsx-2261688415\"><div class=\"jsx-2261688415 _ratio_wrapper\"><a href=\"https://www.tiktok.com/@bp_tiktok/video/6680458801671425281\" class=\"jsx-3808264675 video-feed-item-wrapper\"><span class=\"lazyload-wrapper\"><div style=\"height: 220px;\" class=\"lazyload-placeholder\"></div></span></a></div></div></div><div class=\"jsx-526152079 card-bottom-info\"><div class=\"meta-caption-line\"><h3 class=\"jsx-2276759325 video-meta-title\"><a href=\"/tag/blackpink?lang=en\" class=\"tag-link jsx-231826672\" rel=\"noopener\"><strong class=\"jsx-231826672\">#BLACKPINK </strong></a><strong class=\"jsx-2276759325\"> </strong><a href=\"/tag/%EB%B8%94%EB%9E%99%ED%95%91%ED%81%AC?lang=en\" class=\"tag-link jsx-231826672\" rel=\"noopener\"><strong class=\"jsx-231826672\">#블랙핑크 </strong></a><strong class=\"jsx-2276759325\"> </strong><a href=\"/tag/dontknowwhattodo?lang=en\" class=\"tag-link jsx-231826672\" rel=\"noopener\"><strong class=\"jsx-231826672\">#DontKnowWhatToDo </strong></a><strong class=\"jsx-2276759325\"> </strong><a href=\"/tag/dance_practice?lang=en\" class=\"tag-link jsx-231826672\" rel=\"noopener\"><strong class=\"jsx-231826672\">#DANCE_PRACTICE </strong></a><strong class=\"jsx-2276759325\"> </strong><a href=\"/tag/moving_version?lang=en\" class=\"tag-link jsx-231826672\" rel=\"noopener\"><strong class=\"jsx-231826672\">#MOVING_VERSION </strong></a><strong class=\"jsx-2276759325\"> </strong><a href=\"/tag/%EC%95%88%EB%AC%B4%EC%98%81%EC%83%81?lang=en\" class=\"tag-link jsx-231826672\" rel=\"noopener\"><strong class=\"jsx-231826672\">#안무영상 </strong></a><strong class=\"jsx-2276759325\"> </strong><a href=\"/tag/yg?lang=en\" class=\"tag-link jsx-231826672\" rel=\"noopener\"><strong class=\"jsx-231826672\">#YG </strong></a></h3></div><div class=\"jsx-526152079 play-line\"><div class=\"jsx-526152079 play-icon\"><svg class=\"like-icon\" width=\"16\" height=\"16\" viewBox=\"0 0 48 48\" fill=\"rgba(22, 24, 35, 0.75)\" xmlns=\"http://www.w3.org/2000/svg\"><path fill-rule=\"evenodd\" clip-rule=\"evenodd\" d=\"M16 10.554V37.4459L38.1463 24L16 10.554ZM12 8.77702C12 6.43812 14.5577 4.99881 16.5569 6.21266L41.6301 21.4356C43.5542 22.6038 43.5542 25.3962 41.6301 26.5644L16.5569 41.7873C14.5577 43.0012 12 41.5619 12 39.223V8.77702Z\"></path></svg><strong class=\"jsx-526152079 video-count\">12.9M</strong></div><div class=\"jsx-526152079\">2019-4-17</div></div></div>","link":"https://www.tiktok.com/@bp_tiktok/video/6680458801671425281","retrieved":1629558382503}]}